cryptsh/__init__.py
cryptsh/intents.json
cryptsh/main.py
cryptsh-0.7.dist-info/METADATA
cryptsh-0.7.dist-info/WHEEL
cryptsh-0.7.dist-info/entry_points.txt
cryptsh-0.7.dist-info/top_level.txt
cryptsh-0.7.dist-info/RECORD
