Metadata-Version: 2.1
Name: cryptsh
Version: 0.7
Classifier: Programming Language :: Python :: 3
Classifier: License :: OSI Approved :: MIT License
Classifier: Operating System :: OS Independent
Requires-Dist: python-binance
Requires-Dist: tabulate
Requires-Dist: keyboard
Requires-Dist: psycopg2
Requires-Dist: setuptools
Requires-Dist: supabase
